triessentials/__init__.py
triessentials-0.1.7.dist-info/METADATA
triessentials-0.1.7.dist-info/WHEEL
triessentials-0.1.7.dist-info/RECORD
